aiographql/client/__init__.py
aiographql/client/client.py
aiographql/client/error.py
aiographql/client/exceptions.py
aiographql/client/helpers.py
aiographql/client/request.py
aiographql/client/response.py
aiographql/client/subscription.py
aiographql_client-1.1.0.dist-info/LICENSE
aiographql_client-1.1.0.dist-info/METADATA
aiographql_client-1.1.0.dist-info/WHEEL
aiographql_client-1.1.0.dist-info/RECORD
