Metadata-Version: 2.1
Name: aiographql-client
Version: 1.1.0
Summary: An asyncio GraphQL client built on top of aiohttp and graphql-core-next
Home-page: https://github.com/abn/aiographql-client
License: MIT
Keywords: aiohttp,asyncio,client,graphql,graphql-core,graphql-core-next
Author: Arun Neelicattu
Author-email: arun.neelicattu@gmail.com
Requires-Python: >=3.8,<4.0
Classifier: Framework :: AsyncIO
Classifier: Intended Audience :: Developers
Classifier: License :: OSI Approved :: MIT License
Classifier: Operating System :: OS Independent
Classifier: Programming Language :: Python :: 3
Classifier: Programming Language :: Python :: 3.8
Classifier: Programming Language :: Python :: 3.9
Classifier: Programming Language :: Python :: 3.10
Classifier: Programming Language :: Python :: 3.11
Classifier: Programming Language :: Python :: 3.12
Classifier: Programming Language :: Python :: 3 :: Only
Classifier: Topic :: Software Development :: Libraries :: Python Modules
Requires-Dist: aiohttp (>=3.5,<4.0)
Requires-Dist: cafeteria-asyncio (>=0.3,<0.4)
Requires-Dist: graphql-core (>=3.0,<4.0)
Requires-Dist: ujson (>=2)
Project-URL: Repository, https://github.com/abn/aiographql-client
